pytest_insta/__init__.py
pytest_insta/fixture.py
pytest_insta/format.py
pytest_insta/plugin.py
pytest_insta/py.typed
pytest_insta/review.py
pytest_insta/session.py
pytest_insta/utils.py
pytest_insta-0.4.0.dist-info/WHEEL
pytest_insta-0.4.0.dist-info/entry_points.txt
pytest_insta-0.4.0.dist-info/METADATA
pytest_insta-0.4.0.dist-info/RECORD
