Metadata-Version: 2.4
Name: pytest-insta
Version: 0.4.0
Summary: A practical snapshot testing plugin for pytest
Keywords: pytest-plugin,pytest,testing,snapshot,snapshot-testing
Author: Valentin Berlier
Author-email: Valentin Berlier <berlier.v@gmail.com>
License-Expression: MIT
Classifier: Framework :: Pytest
Requires-Dist: pytest>=9.0.0
Requires-Dist: wrapt>=2.0.1
Requires-Python: >=3.14
